{
  "displayName": "Transnational AQMS Dashboard",
  "mosaicLayout": {
    "columns": 12,
    "tiles": [
      {
        "width": 6,
        "height": 4,
        "widget": {
          "title": "Cloud Run Request Count",
          "xyChart": {
            "dataSets": [
              {
                "timeSeriesQuery": {
                  "timeSeriesFilter": {
                    "filter": "resource.type=\"cloud_run_revision\" metric.type=\"run.googleapis.com/request_count\"",
                    "aggregation": {
                      "alignmentPeriod": "60s",
                      "perSeriesAligner": "ALIGN_RATE"
                    }
                  }
                }
              }
            ]
          }
        }
      }
    ]
  }
}
